gyver/__init__.py
gyver/config/__init__.py
gyver/config/adapter/__init__.py
gyver/config/adapter/attrs.py
gyver/config/adapter/dataclass.py
gyver/config/adapter/factory.py
gyver/config/adapter/gattrs.py
gyver/config/adapter/helpers.py
gyver/config/adapter/interface.py
gyver/config/adapter/mark.py
gyver/config/adapter/memo.py
gyver/config/adapter/pydantic.py
gyver/context/__init__.py
gyver/context/atomic_/__init__.py
gyver/context/atomic_/bound.py
gyver/context/atomic_/core.py
gyver/context/atomic_/resolver.py
gyver/context/context.py
gyver/context/interfaces/__init__.py
gyver/context/interfaces/adapter.py
gyver/context/typedef.py
gyver/ds/__init__.py
gyver/ds/circuit.py
gyver/exc.py
gyver/filetree/__init__.py
gyver/filetree/filetree.py
gyver/filetree/helpers.py
gyver/filetree/interface.py
gyver/filetree/typedef.py
gyver/filetree/virtual.py
gyver/model/__init__.py
gyver/model/v1.py
gyver/model/v2.py
gyver/pools/__init__.py
gyver/pools/asyncio.py
gyver/pools/resource.py
gyver/pools/thread.py
gyver/py.typed
gyver/url/__init__.py
gyver/url/core.py
gyver/url/encode.py
gyver/url/fragment.py
gyver/url/netloc.py
gyver/url/path.py
gyver/url/query.py
gyver/url/utils.py
gyver/utils.py
gyver-5.2.0.dist-info/LICENSE
gyver-5.2.0.dist-info/METADATA
gyver-5.2.0.dist-info/WHEEL
gyver-5.2.0.dist-info/RECORD
